tapdata_sdk/__init__.py
tapdata_sdk/client.py
tapdata_sdk/enums.py
tapdata_sdk/exceptions.py
tapdata_sdk/models.py
tapdata_sdk/utils.py
tapdata_sdk-0.1.0.dist-info/licenses/LICENSE
tapdata_sdk-0.1.0.dist-info/METADATA
tapdata_sdk-0.1.0.dist-info/WHEEL
tapdata_sdk-0.1.0.dist-info/top_level.txt
tapdata_sdk-0.1.0.dist-info/RECORD
