Metadata-Version: 2.4
Name: tapdata_sdk
Version: 0.1.0
Summary: A Python client library for interacting with Tapdata API
Author-email: doubled <309294891@qq.com>
License: MIT
Project-URL: Homepage, https://github.com/lddlww/tapdata_sdk
Project-URL: Documentation, https://github.com/lddlww/tapdata_sdk#readme
Project-URL: Repository, https://github.com/lddlww/tapdata_sdk
Project-URL: Issues, https://github.com/lddlww/tapdata_sdk/issues
Keywords: tapdata,api,client,sdk,data-integration
Classifier: Development Status :: 4 - Beta
Classifier: Intended Audience :: Developers
Classifier: License :: OSI Approved :: MIT License
Classifier: Programming Language :: Python :: 3
Classifier: Programming Language :: Python :: 3.7
Classifier: Programming Language :: Python :: 3.8
Classifier: Programming Language :: Python :: 3.9
Classifier: Programming Language :: Python :: 3.10
Classifier: Programming Language :: Python :: 3.11
Classifier: Programming Language :: Python :: 3.12
Classifier: Topic :: Software Development :: Libraries :: Python Modules
Requires-Python: >=3.7
License-File: LICENSE
Requires-Dist: requests>=2.25.0
Requires-Dist: pycryptodome>=3.10.0
Provides-Extra: dev
Requires-Dist: pytest>=7.0.0; extra == "dev"
Requires-Dist: pytest-cov>=3.0.0; extra == "dev"
Requires-Dist: black>=22.0.0; extra == "dev"
Requires-Dist: isort>=5.10.0; extra == "dev"
Requires-Dist: flake8>=4.0.0; extra == "dev"
Requires-Dist: mypy>=0.950; extra == "dev"
Requires-Dist: types-requests>=2.25.0; extra == "dev"
Dynamic: license-file
